scbean/__init__.py
scbean/model/__init__.py
scbean/model/davae.py
scbean/model/vimcca.py
scbean/model/vipcca.py
scbean/model/visgp.py
scbean/tools/__init__.py
scbean/tools/parser.py
scbean/tools/plotting.py
scbean/tools/qqnorm.py
scbean/tools/transferLabel.py
scbean/tools/utils.py
scbean-0.5.5.dist-info/METADATA
scbean-0.5.5.dist-info/RECORD
scbean-0.5.5.dist-info/WHEEL
scbean-0.5.5.dist-info/top_level.txt
