Metadata-Version: 2.1
Name: scbean
Version: 0.5.5
Summary: integration
Home-page: https://github.com/jhu99/scbean
Author: Jialu Hu
Author-email: jhu@nwpu.edu.cn
License: MIT
Platform: UNKNOWN
Requires-Python: >=3.6
Requires-Dist: scanpy
Requires-Dist: tensorflow (==2.4.0)
Requires-Dist: anndata
Requires-Dist: scipy
Requires-Dist: pandas
Requires-Dist: seaborn
Requires-Dist: keras (==2.3.1)
Requires-Dist: python-igraph
Requires-Dist: louvain
Requires-Dist: h5py
